django_kpi/__init__.py
django_kpi/admin.py
django_kpi/apps.py
django_kpi/forms.py
django_kpi/models.py
django_kpi/tests.py
django_kpi/urls.py
django_kpi/utils.py
django_kpi/views.py
django_kpi/migrations/0001_initial.py
django_kpi/migrations/__init__.py
django_kpi/static/js/kpi_admin.js
django_kpi-1.0.0.dist-info/METADATA
django_kpi-1.0.0.dist-info/WHEEL
django_kpi-1.0.0.dist-info/top_level.txt
django_kpi-1.0.0.dist-info/RECORD
