Metadata-Version: 2.2
Name: django-kpi
Version: 1.0.0
Summary: designed to create flexible Key Performance Indicators (KPIs) for your projects.
Author-email: Mohammed CHAHBOUN <mchahboun@majaracapital.com>
Project-URL: Homepage, https://github.com/M97Chahboun/django_kpi
Classifier: Environment :: Web Environment
Classifier: Framework :: Django
Classifier: Framework :: Django :: 3.2
Classifier: Intended Audience :: Developers
Classifier: License :: OSI Approved :: BSD License
Classifier: Operating System :: OS Independent
Classifier: Programming Language :: Python
Classifier: Programming Language :: Python :: 3
Classifier: Programming Language :: Python :: 3 :: Only
Classifier: Programming Language :: Python :: 3.10
Classifier: Programming Language :: Python :: 3.11
Classifier: Programming Language :: Python :: 3.12
Classifier: Topic :: Internet :: WWW/HTTP
Classifier: Topic :: Internet :: WWW/HTTP :: Dynamic Content
Requires-Python: >=3.10
Requires-Dist: django>=3.2
